code42cli/__init__.py
code42cli/__main__.py
code42cli/__version__.py
code42cli/bulk.py
code42cli/config.py
code42cli/date_helper.py
code42cli/enums.py
code42cli/errors.py
code42cli/file_readers.py
code42cli/main.py
code42cli/maps.py
code42cli/options.py
code42cli/output_formats.py
code42cli/password.py
code42cli/profile.py
code42cli/sdk_client.py
code42cli/util.py
code42cli/worker.py
code42cli/click_ext/__init__.py
code42cli/click_ext/groups.py
code42cli/click_ext/options.py
code42cli/click_ext/types.py
code42cli/cmds/__init__.py
code42cli/cmds/alert_rules.py
code42cli/cmds/alerts.py
code42cli/cmds/auditlogs.py
code42cli/cmds/cases.py
code42cli/cmds/devices.py
code42cli/cmds/legal_hold.py
code42cli/cmds/profile.py
code42cli/cmds/securitydata.py
code42cli/cmds/shared.py
code42cli/cmds/shell.py
code42cli/cmds/trustedactivities.py
code42cli/cmds/users.py
code42cli/cmds/util.py
code42cli/cmds/watchlists.py
code42cli/cmds/search/__init__.py
code42cli/cmds/search/cursor_store.py
code42cli/cmds/search/options.py
code42cli/extensions/__init__.py
code42cli/logger/__init__.py
code42cli/logger/enums.py
code42cli/logger/formatters.py
code42cli/logger/handlers.py
code42cli-1.19.0.dist-info/LICENSE.md
code42cli-1.19.0.dist-info/METADATA
code42cli-1.19.0.dist-info/WHEEL
code42cli-1.19.0.dist-info/entry_points.txt
code42cli-1.19.0.dist-info/top_level.txt
code42cli-1.19.0.dist-info/RECORD
