Metadata-Version: 2.1
Name: code42cli
Version: 1.19.0
Summary: The official command line tool for interacting with Code42
Home-page: https://github.com/code42/py42
License: UNKNOWN
Project-URL: Issue Tracker, https://github.com/code42/code42cli/issues
Project-URL: Documentation, https://clidocs.code42.com/
Project-URL: Source Code, https://github.com/code42/code42cli
Platform: UNKNOWN
Classifier: Intended Audience :: Developers
Classifier: Natural Language :: English
Classifier: License :: OSI Approved :: MIT License
Classifier: Programming Language :: Python
Classifier: Programming Language :: Python :: 3
Classifier: Programming Language :: Python :: 3.9
Classifier: Programming Language :: Python :: 3.10
Classifier: Programming Language :: Python :: 3.11
Classifier: Programming Language :: Python :: 3.12
Classifier: Programming Language :: Python :: Implementation :: CPython
Requires-Python: >=3.9, <4
License-File: LICENSE.md
Requires-Dist: chardet
Requires-Dist: click>=7.1.1
Requires-Dist: click-plugins>=1.1.1
Requires-Dist: colorama>=0.4.3
Requires-Dist: keyring==18.0.1
Requires-Dist: keyrings.alt==3.2.0
Requires-Dist: pandas>=1.1.3
Requires-Dist: py42>=1.28.0
Requires-Dist: setuptools>=66.0.0
Requires-Dist: ipython>=7.16.3; python_version < "3.8"
Requires-Dist: ipython>=8.10.0; python_version >= "3.8"
Provides-Extra: dev
Requires-Dist: flake8>=4.0.0; extra == "dev"
Requires-Dist: pytest==4.6.11; extra == "dev"
Requires-Dist: pytest-cov==2.10.0; extra == "dev"
Requires-Dist: pytest-mock==2.0.0; extra == "dev"
Requires-Dist: tox>=3.17.1; extra == "dev"
Requires-Dist: importlib-metadata<5.0; extra == "dev"
Provides-Extra: docs
Requires-Dist: sphinx==8.1.3; extra == "docs"
Requires-Dist: myst-parser==4.0.0; extra == "docs"
Requires-Dist: sphinx-rtd-theme==3.0.2; extra == "docs"
Requires-Dist: sphinx-click; extra == "docs"
